[
  {
    "OrderID": 10248,
    "ProductID": 11,
    "UnitPrice": 14.0,
    "Quantity": 12,
    "Discount": 0.0
  },
  {
    "OrderID": 10248,
    "ProductID": 42,
    "UnitPrice": 9.8,
    "Quantity": 10,
    "Discount": 0.0
  },
  {
    "OrderID": 10248,
    "ProductID": 72,
    "UnitPrice": 34.8,
    "Quantity": 5,
    "Discount": 0.0
  },
  {
    "OrderID": 10249,
    "ProductID": 14,
    "UnitPrice": 18.6,
    "Quantity": 9,
    "Discount": 0.0
  },
  {
    "OrderID": 10249,
    "ProductID": 51,
    "UnitPrice": 42.4,
    "Quantity": 40,
    "Discount": 0.0
  },
  {
    "OrderID": 10250,
    "ProductID": 41,
    "UnitPrice": 7.7,
    "Quantity": 10,
    "Discount": 0.0
  },
  {
    "OrderID": 10250,
    "ProductID": 51,
    "UnitPrice": 42.4,
    "Quantity": 35,
    "Discount": 0.15
  },
  {
    "OrderID": 10250,
    "ProductID": 65,
    "UnitPrice": 16.8,
    "Quantity": 15,
    "Discount": 0.15
  },
  {
    "OrderID": 10251,
    "ProductID": 22,
    "UnitPrice": 16.8,
    "Quantity": 6,
    "Discount": 0.05
  },
  {
    "OrderID": 10251,
    "ProductID": 57,
    "UnitPrice": 15.6,
    "Quantity": 15,
    "Discount": 0.05
  },
  {
    "OrderID": 10251,
    "ProductID": 65,
    "UnitPrice": 16.8,
    "Quantity": 20,
    "Discount": 0.0
  },
  {
    "OrderID": 10252,
    "ProductID": 20,
    "UnitPrice": 64.8,
    "Quantity": 40,
    "Discount": 0.05
  },
  {
    "OrderID": 10252,
    "ProductID": 33,
    "UnitPrice": 2.0,
    "Quantity": 25,
    "Discount": 0.05
  },
  {
    "OrderID": 10252,
    "ProductID": 60,
    "UnitPrice": 27.2,
    "Quantity": 40,
    "Discount": 0.0
  },
  {
    "OrderID": 10253,
    "ProductID": 31,
    "UnitPrice": 10.0,
    "Quantity": 20,
    "Discount": 0.0
  },
  {
    "OrderID": 10253,
    "ProductID": 39,
    "UnitPrice": 14.4,
    "Quantity": 42,
    "Discount": 0.0
  },
  {
    "OrderID": 10253,
    "ProductID": 49,
    "UnitPrice": 16.0,
    "Quantity": 40,
    "Discount": 0.0
  },
  {
    "OrderID": 10254,
    "ProductID": 24,
    "UnitPrice": 3.6,
    "Quantity": 15,
    "Discount": 0.15
  },
  {
    "OrderID": 10254,
    "ProductID": 55,
    "UnitPrice": 19.2,
    "Quantity": 21,
    "Discount": 0.15
  },
  {
    "OrderID": 10254,
    "ProductID": 74,
    "UnitPrice": 8.0,
    "Quantity": 21,
    "Discount": 0.0
  },
  {
    "OrderID": 10255,
    "ProductID": 2,
    "UnitPrice": 15.2,
    "Quantity": 20,
    "Discount": 0.0
  },
  {
    "OrderID": 10255,
    "ProductID": 16,
    "UnitPrice": 13.9,
    "Quantity": 35,
    "Discount": 0.0
  },
  {
    "OrderID": 10255,
    "ProductID": 36,
    "UnitPrice": 15.2,
    "Quantity": 25,
    "Discount": 0.0
  },
  {
    "OrderID": 10255,
    "ProductID": 59,
    "UnitPrice": 44.0,
    "Quantity": 30,
    "Discount": 0.0
  },
  {
    "OrderID": 10256,
    "ProductID": 53,
    "UnitPrice": 26.2,
    "Quantity": 15,
    "Discount": 0.0
  },
  {
    "OrderID": 10256,
    "ProductID": 77,
    "UnitPrice": 10.4,
    "Quantity": 12,
    "Discount": 0.0
  },
  {
    "OrderID": 10257,
    "ProductID": 27,
    "UnitPrice": 35.1,
    "Quantity": 25,
    "Discount": 0.0
  },
  {
    "OrderID": 10257,
    "ProductID": 39,
    "UnitPrice": 14.4,
    "Quantity": 6,
    "Discount": 0.0
  },
  {
    "OrderID": 10257,
    "ProductID": 77,
    "UnitPrice": 10.4,
    "Quantity": 15,
    "Discount": 0.0
  }
]
